autodocumentation_python/__init__.py
autodocumentation_python/check_config.py
autodocumentation_python/clone_source.py
autodocumentation_python/cost_estimator.py
autodocumentation_python/create_docstrings.py
autodocumentation_python/gptapi.py
autodocumentation_python/insert_docstrings.py
autodocumentation_python/main.py
autodocumentation_python/make_snippets.py
autodocumentation_python/summarize_file.py
autodocumentation_python/summarize_repo.py
autodocumentation_python-2.0.dist-info/LICENSE.txt
autodocumentation_python-2.0.dist-info/METADATA
autodocumentation_python-2.0.dist-info/WHEEL
autodocumentation_python-2.0.dist-info/entry_points.txt
autodocumentation_python-2.0.dist-info/top_level.txt
autodocumentation_python-2.0.dist-info/RECORD
