Metadata-Version: 2.1
Name: autodocumentation-python
Version: 2.0
Summary: Automated documentationstring generation for python files within repositories, folders or for sinlge .py files.
Home-page: https://github.com/StructuralNeurobiologyLab/autodoc
Author: Karl Heggenberger, Joergen Kornfeld.
Author-email: Karl_Heggenberger@LinkedIn.com
License: UNKNOWN
Download-URL: https://github.com/StructuralNeurobiologyLab/autodoc
Platform: UNKNOWN
Requires-Dist: GitPython
Requires-Dist: astunparse
Requires-Dist: openai
Requires-Dist: pyyaml
